sessender.py
sessender-1.1.0.dist-info/LICENSE
sessender-1.1.0.dist-info/METADATA
sessender-1.1.0.dist-info/WHEEL
sessender-1.1.0.dist-info/top_level.txt
sessender-1.1.0.dist-info/RECORD
