Metadata-Version: 2.1
Name: sessender
Version: 1.1.0
Summary: A Python package for sending emails using AWS SES
Home-page: https://github.com/amitsdalal/sessender
Author: Amit Dalal
License: UNKNOWN
Platform: UNKNOWN
Classifier: Programming Language :: Python :: 3
Classifier: License :: OSI Approved :: MIT License
Classifier: Operating System :: OS Independent
License-File: LICENSE
